hierarchical_permissions/__init__.py
hierarchical_permissions/apps.py
hierarchical_permissions/conf.py
hierarchical_permissions/decorators.py
hierarchical_permissions/defaults.py
hierarchical_permissions/form.py
hierarchical_permissions/migrations/__init__.py
hierarchical_permissions/mixins.py
hierarchical_permissions/models.py
hierarchical_permissions/services.py
hierarchical_permissions/utils.py
django_hierarchical_permissions-0.0.1.dist-info/METADATA
django_hierarchical_permissions-0.0.1.dist-info/WHEEL
django_hierarchical_permissions-0.0.1.dist-info/RECORD
