Metadata-Version: 2.3
Name: django-hierarchical-permissions
Version: 0.0.1
Summary: 
Keywords: django,permissions,rbac,hierarchy,rules
Author: JakubJakacki18
Author-email: jakub.jakacki18@gmail.com
Requires-Python: >=3.12,<4.0
Classifier: Development Status :: 3 - Alpha
Classifier: Framework :: Django
Classifier: Programming Language :: Python :: 3
Classifier: Programming Language :: Python :: 3.12
Classifier: License :: OSI Approved :: MIT License
Classifier: Operating System :: OS Independent
Requires-Dist: django (>=5.2.3,<6.0.0)
Requires-Dist: django-mptt (>=0.17.0,<0.18.0)
Requires-Dist: rules (>=3.5,<4.0)
